megyr/__init__.py
megyr/config_validation.py
megyr/gyre.py
megyr/mesa.py
megyr/oscillations_summary.py
megyr/parameters.py
megyr/profile.py
megyr/util.py
megyr-0.2.1.dist-info/METADATA
megyr-0.2.1.dist-info/RECORD
megyr-0.2.1.dist-info/WHEEL
megyr-0.2.1.dist-info/top_level.txt
