Metadata-Version: 2.1
Name: megyr
Version: 0.2.1
Summary: A library for creating scripts to automate MESA and GYRE runs.
Home-page: https://github.com/ExcaliburZero/megyr
Author: Christopher Wells
Author-email: cwells2@oswego.edu
License: MIT
Platform: UNKNOWN
Requires-Dist: pandas
Requires-Dist: pystache
